pylm_foundry/__init__.py
pylm_foundry/core.cpython-313-x86_64-linux-gnu.so
pylm_foundry/core.pyx
pylm_foundry/main.py
pylm_foundry-0.1.2.dist-info/METADATA
pylm_foundry-0.1.2.dist-info/WHEEL
pylm_foundry-0.1.2.dist-info/entry_points.txt
pylm_foundry-0.1.2.dist-info/top_level.txt
pylm_foundry-0.1.2.dist-info/RECORD
