Metadata-Version: 2.4
Name: pylm-foundry
Version: 0.1.2
Summary: A Python-based license manager foundry
Author: HSIAOLIN
Maintainer-email: HSIAOLIN <sjzshmh@163.com>
License-Expression: MIT
Keywords: license,manager,foundry
Classifier: Development Status :: 4 - Beta
Classifier: Intended Audience :: Developers
Classifier: Programming Language :: Python :: 3
Classifier: Programming Language :: Python :: 3.10
Requires-Python: >=3.10
Requires-Dist: click
Requires-Dist: cryptography
Requires-Dist: py-machineid
